{
  "kind": "collectionType",
  "collectionName": "article_categories",
  "info": {
    "singularName": "article-category",
    "pluralName": "article-categories",
    "displayName": "ArticleCategory",
    "description": ""
  },
  "options": {
    "draftAndPublish": false
  },
  "pluginOptions": {},
  "attributes": {
    "title": {
      "type": "string",
      "required": true
    },
    "description": {
      "type": "text"
    },
    "slug": {
      "type": "string"
    },
    "navigation_item": {
      "type": "relation",
      "relation": "oneToOne",
      "target": "api::navigation.navigation"
    },
    "articles": {
      "type": "relation",
      "relation": "oneToMany",
      "target": "api::article.article",
      "mappedBy": "article_category"
    }
  }
}
